greedy_ancestral_search/__init__.py
greedy_ancestral_search/core.py
greedy_ancestral_search/sets.py
greedy_ancestral_search/utils.py
greedy_ancestral_search-0.0.4.dist-info/METADATA
greedy_ancestral_search-0.0.4.dist-info/WHEEL
greedy_ancestral_search-0.0.4.dist-info/licenses/LICENSE.md
greedy_ancestral_search-0.0.4.dist-info/RECORD
