Metadata-Version: 2.4
Name: greedy-ancestral-search
Version: 0.0.4
Summary: Python implementation of the Greedy Ancestral Seach (GAS) algorithm from the paper 'On the Number of Conditional Independence Tests in Constraint-based Causal Discovery'.
Project-URL: Repository, https://github.com/uhlerlab/greedy-ancestral-search
Project-URL: Issues, https://github.com/uhlerlab/greedy-ancestral-search/issues
Author: Marc Franquesa Monés, Jiaqi Zhang, Caroline Uhler
License-Expression: MIT
License-File: LICENSE.md
Keywords: causal discovery,constraint-based causal discovery
Classifier: License :: OSI Approved :: MIT License
Classifier: Operating System :: OS Independent
Classifier: Programming Language :: Python :: 3.10
Classifier: Programming Language :: Python :: 3.11
Classifier: Programming Language :: Python :: 3.12
Classifier: Programming Language :: Python :: 3.13
Requires-Python: >=3.10
Requires-Dist: networkx>=3.4.2
